README.rst
setup.py
flatdb/__init__.py
flatdb/app.py
flatdb/run.py
flatdb.egg-info/PKG-INFO
flatdb.egg-info/SOURCES.txt
flatdb.egg-info/dependency_links.txt
flatdb.egg-info/entry_points.txt
flatdb.egg-info/not-zip-safe
flatdb.egg-info/requires.txt
flatdb.egg-info/top_level.txt