Metadata-Version: 1.1
Name: flatdb
Version: 0.1.0
Summary: HTTP access to a LevelDB.
Home-page: https://github.com/todaysmeet/flatdb
Author: James Socol
Author-email: james@todaysmeet.com
License: Apache Software License
Platform: UNKNOWN
Classifier: Development Status :: 4 - Beta
Classifier: Intended Audience :: Developers
Classifier: License :: OSI Approved :: Apache Software License
Classifier: Operating System :: OS Independent
Classifier: Programming Language :: Python
Classifier: Programming Language :: Python :: 2.6
Classifier: Programming Language :: Python :: 2.7
